README.md
setup.py
montpellier_biking/__init__.py
montpellier_biking.egg-info/PKG-INFO
montpellier_biking.egg-info/SOURCES.txt
montpellier_biking.egg-info/dependency_links.txt
montpellier_biking.egg-info/not-zip-safe
montpellier_biking.egg-info/top_level.txt
montpellier_biking/io/Load_db.py
montpellier_biking/io/__init__.py
montpellier_biking/model/__init__.py
montpellier_biking/model/counters.py
montpellier_biking/vis/__init__.py
montpellier_biking/vis/animation.py
montpellier_biking/vis/program.py