Metadata-Version: 1.0
Name: montpellier-biking
Version: 0.1.0
Summary: Visualization of the bicycle flux in Montpellier
Home-page: https://github.com/Poncheele/Montpellier_Biking
Author: Alleau Julie, Chaoui Wiam, Poncheele Clement et Seck, Gade
Author-email: julie.alleau@etu.umontpellier.fr
License: MIT
Platform: UNKNOWN
